moevat/__init__.py
moevat/annotator.py
moevat/cli.py
moevat/version.py
moevat-1.1.1.dist-info/LICENSE
moevat-1.1.1.dist-info/METADATA
moevat-1.1.1.dist-info/WHEEL
moevat-1.1.1.dist-info/entry_points.txt
moevat-1.1.1.dist-info/top_level.txt
moevat-1.1.1.dist-info/RECORD
