Metadata-Version: 2.1
Name: moevat
Version: 1.1.1
Summary: Python libary to quickly label data/images.
Home-page: https://github.com/mhamdan91/moevat
Author: mhamdan91 (Hamdan, Muhammad)
Author-email: <mhamdan.dev@gmail.com>
Keywords: python,gui,labeling,machine-learning,labeler,classification,images,annotation
Classifier: Development Status :: 5 - Production/Stable
Classifier: Intended Audience :: Developers
Classifier: Programming Language :: Python :: 3
Classifier: Operating System :: Unix
Classifier: Operating System :: MacOS :: MacOS X
Classifier: Operating System :: Microsoft :: Windows
Classifier: License :: OSI Approved :: MIT License
License-File: LICENSE
Requires-Dist: opencv-python (==4.6.0.66)
Requires-Dist: numpy (==1.21.6)
Requires-Dist: click (==8.0.1)
Requires-Dist: PyYAML (==6.0)
Requires-Dist: moethread
Requires-Dist: screeninfo
Requires-Dist: pynput
